MANIFEST.in
README.md
setup.py
djangocms_social/__init__.py
djangocms_social/cms_plugins.py
djangocms_social/defaults.py
djangocms_social.egg-info/PKG-INFO
djangocms_social.egg-info/SOURCES.txt
djangocms_social.egg-info/dependency_links.txt
djangocms_social.egg-info/not-zip-safe
djangocms_social.egg-info/requires.txt
djangocms_social.egg-info/top_level.txt
djangocms_social/migrations/0001_initial.py
djangocms_social/migrations/0002_auto__add_field_like_image.py
djangocms_social/migrations/0003_auto__add_mail.py
djangocms_social/migrations/0004_auto__add_links.py
djangocms_social/migrations/__init__.py
djangocms_social/models/__init__.py
djangocms_social/models/base.py
djangocms_social/models/likes.py
djangocms_social/static/djangocms_social/icons/facebook_link.png
djangocms_social/static/djangocms_social/icons/linkedin_link.png
djangocms_social/static/djangocms_social/icons/rss_link.png
djangocms_social/static/djangocms_social/icons/twitter_link.png
djangocms_social/static/djangocms_social/icons/xing_link.png
djangocms_social/templates/djangocms_social/plugins/like.html
djangocms_social/templates/djangocms_social/plugins/links.html
djangocms_social/templates/djangocms_social/plugins/mail.html
djangocms_social/templates/djangocms_social/plugins/likes/facebook.html
djangocms_social/templates/djangocms_social/plugins/likes/google.html