Metadata-Version: 1.0
Name: djangocms-social
Version: 0.4a.1
Summary: Social plugin for django-cms.
Home-page: https://github.com/pascalmouret/djangocms-social
Author: Pascal Mouret
Author-email: pascal.mouret@divio.ch
License: UNKNOWN
Platform: OS Independent
Classifier: Environment :: Web Environment
Classifier: Framework :: Django
Classifier: Intended Audience :: Developers
Classifier: License :: OSI Approved :: BSD License
Classifier: Operating System :: OS Independent
Classifier: Programming Language :: Python
Classifier: Topic :: Internet :: WWW/HTTP :: Dynamic Content
Classifier: Topic :: Software Development
Classifier: Topic :: Software Development :: Libraries :: Application Frameworks
Classifier: Development Status :: 3 - Alpha
